okama/__init__.py
okama/api/__init__.py
okama/api/api_methods.py
okama/api/data_queries.py
okama/api/namespaces.py
okama/api/search.py
okama/asset.py
okama/asset_list.py
okama/common/__init__.py
okama/common/error.py
okama/common/helpers/__init__.py
okama/common/helpers/helpers.py
okama/common/helpers/ratios.py
okama/common/helpers/rebalancing.py
okama/common/make_asset_list.py
okama/common/solver.py
okama/common/validators.py
okama/frontier/__init__.py
okama/frontier/multi_period.py
okama/frontier/single_period.py
okama/macro.py
okama/portfolio.py
okama/settings.py
okama-1.5.0.dist-info/LICENSE.txt
okama-1.5.0.dist-info/METADATA
okama-1.5.0.dist-info/WHEEL
okama-1.5.0.dist-info/RECORD
