Metadata-Version: 2.3
Name: okama
Version: 1.5.0
Summary: Investment portfolio analyzing & optimization tools
License: MIT
Keywords: finance,investments,efficient frontier,python,optimization
Author: Sergey Kikevich
Author-email: chilango74@gmail.com
Requires-Python: >=3.10,<4.0.0
Classifier: Development Status :: 5 - Production/Stable
Classifier: Intended Audience :: Developers
Classifier: Intended Audience :: End Users/Desktop
Classifier: Intended Audience :: Financial and Insurance Industry
Classifier: Intended Audience :: Science/Research
Classifier: License :: OSI Approved :: MIT License
Classifier: Operating System :: OS Independent
Classifier: Programming Language :: Python :: 3
Classifier: Programming Language :: Python :: 3.10
Classifier: Programming Language :: Python :: 3.11
Classifier: Programming Language :: Python :: 3.12
Classifier: Programming Language :: Python :: 3.13
Classifier: Programming Language :: Python :: 3 :: Only
Classifier: Programming Language :: Python :: 3.8
Classifier: Programming Language :: Python :: 3.9
Classifier: Topic :: Scientific/Engineering :: Mathematics
Classifier: Topic :: Software Development :: Libraries :: Python Modules
Requires-Dist: joblib
Requires-Dist: matplotlib (>=3.5.1)
Requires-Dist: pandas (>=2.0.0,<3.0.0)
Requires-Dist: pandas-stubs
Requires-Dist: requests
Requires-Dist: scipy (>=1.9.0)
Project-URL: Documentation, https://okama.readthedocs.io/en/master
Project-URL: Homepage, https://okama.io
Project-URL: Repository, https://github.com/mbk-dev/okama
